resolve_robotics_uri_py/__init__.py
resolve_robotics_uri_py/resolve_robotics_uri_py.py
resolve_robotics_uri_py-0.3.1.dist-info/LICENSE
resolve_robotics_uri_py-0.3.1.dist-info/METADATA
resolve_robotics_uri_py-0.3.1.dist-info/WHEEL
resolve_robotics_uri_py-0.3.1.dist-info/entry_points.txt
resolve_robotics_uri_py-0.3.1.dist-info/top_level.txt
resolve_robotics_uri_py-0.3.1.dist-info/RECORD
