Metadata-Version: 2.2
Name: resolve-robotics-uri-py
Version: 0.3.1
Summary: Pure python package to solve ROS-style package:// and Gazebo-style model:// URIs in absolute paths.
Home-page: https://github.com/ami-iit/resolve-robotics-uri-py
Author: Silvio Traversaro
Author-email: silvio.traversaro@iit.it
License: BSD
Project-URL: Changelog, https://github.com/ami-iit/resolve-robotics-uri-py/releases
Project-URL: Source, https://github.com/ami-iit/resolve-robotics-uri-py
Project-URL: Tracker, https://github.com/ami-iit/resolve-robotics-uri-py/issues
Platform: any
Classifier: Development Status :: 4 - Beta
Classifier: Intended Audience :: Developers
Classifier: License :: OSI Approved :: BSD License
Classifier: Operating System :: POSIX :: Linux
Classifier: Operating System :: MacOS
Classifier: Operating System :: Microsoft
Classifier: Programming Language :: Python :: 3.8
Classifier: Programming Language :: Python :: 3.9
Classifier: Programming Language :: Python :: 3.10
Classifier: Programming Language :: Python :: 3.11
Classifier: Programming Language :: Python :: 3 :: Only
Classifier: Programming Language :: Python :: Implementation :: CPython
Classifier: Topic :: Software Development
Requires-Python: >=3.9
License-File: LICENSE
Provides-Extra: style
Requires-Dist: black; extra == "style"
Requires-Dist: isort; extra == "style"
Provides-Extra: testing
Provides-Extra: all
Requires-Dist: black; extra == "all"
Requires-Dist: isort; extra == "all"
